herborist/__init__.py
herborist/_version.py
herborist/herborist.py
herborist/herborist.ui
herborist-3.3.2.dist-info/LICENSE
herborist-3.3.2.dist-info/METADATA
herborist-3.3.2.dist-info/WHEEL
herborist-3.3.2.dist-info/entry_points.txt
herborist-3.3.2.dist-info/top_level.txt
herborist-3.3.2.dist-info/RECORD
