Metadata-Version: 2.1
Name: herborist
Version: 3.3.2
Summary: Graphical tool to detect and configure Dynamixel motors
Home-page: https://github.com/poppy-project/herborist
Author: See https://github.com/poppy-project/herborist/graphs/contributors
Author-email: dev@poppy-station.org
License: GNU GENERAL PUBLIC LICENSE Version 3
Platform: UNKNOWN
Classifier: Programming Language :: Python :: 3
Classifier: Topic :: Scientific/Engineering
Requires-Dist: numpy
Requires-Dist: pypot
Requires-Dist: pyqt5
Provides-Extra: doc
Requires-Dist: sphinx ; extra == 'doc'
Requires-Dist: sphinx-bootstrap-theme ; extra == 'doc'
Requires-Dist: sphinxjp.themes.basicstrap ; extra == 'doc'
